propsettings/__init__.py
propsettings/configurable.py
propsettings/decorator.py
propsettings/setting.py
propsettings/setting_type.py
propsettings/decorators/__init__.py
propsettings/setting_types/__init__.py
propsettings/setting_types/list_setting_type.py
propsettings/setting_types/password_setting_type.py
propsettings/setting_types/path_setting_type.py
propsettings/setting_types/range_setting_type.py
propsettings/setting_types/selectable_setting_type.py
propsettings-0.1.15.dist-info/LICENSE
propsettings-0.1.15.dist-info/METADATA
propsettings-0.1.15.dist-info/WHEEL
propsettings-0.1.15.dist-info/top_level.txt
propsettings-0.1.15.dist-info/RECORD
