Metadata-Version: 2.1
Name: propsettings
Version: 0.1.15
Summary: A python package to define how a class member should be rendered in a UI.
Home-page: https://github.com/mnicolas94/propsettings
Author: Miguel Nicolás-Díaz
Author-email: miguelcok27@gmail.com
License: UNKNOWN
Platform: UNKNOWN
Classifier: Programming Language :: Python :: 3
Classifier: License :: OSI Approved :: MIT License
Classifier: Operating System :: OS Independent
Classifier: Development Status :: 3 - Alpha
Classifier: Intended Audience :: Developers
Requires-Python: >=3.6
License-File: LICENSE
Requires-Dist: pyyaml
